{"reward": {"agent_1": [], "agent_2": [], "agent_3": [], "agent_4": [], "agent_5": [], "agent_6": [], "agent_7": [], "agent_8": [], "agent_9": [], "agent_10": [], "agent_11": [], "agent_12": [], "agent_13": [], "agent_14": [], "agent_15": [], "agent_16": [], "agent_17": [], "agent_18": [], "agent_19": [], "agent_20": []}, "utilization_rate": {"agent_1": [], "agent_2": [], "agent_3": [], "agent_4": [], "agent_5": [], "agent_6": [], "agent_7": [], "agent_8": [], "agent_9": [], "agent_10": [], "agent_11": [], "agent_12": [], "agent_13": [], "agent_14": [], "agent_15": [], "agent_16": [], "agent_17": [], "agent_18": [], "agent_19": [], "agent_20": []}, "makespan": {"episode_0": 1379, "episode_1": 1440, "episode_2": 1340, "episode_3": 1242, "episode_4": 1369, "episode_5": 1410, "episode_6": 1299, "episode_7": 1433, "episode_8": 1362, "episode_9": 1368, "episode_10": 1373, "episode_11": 1293, "episode_12": 1363, "episode_13": 1302, "episode_14": 1289, "episode_15": 1320, "episode_16": 1295, "episode_17": 1284, "episode_18": 1457, "episode_19": 1420, "episode_20": 1295, "episode_21": 1370, "episode_22": 1487, "episode_23": 1304, "episode_24": 1288, "episode_25": 1320, "episode_26": 1351, "episode_27": 1475, "episode_28": 1315, "episode_29": 1411, "episode_30": 1294, "episode_31": 1281, "episode_32": 1372, "episode_33": 1418, "episode_34": 1340, "episode_35": 1449, "episode_36": 1536, "episode_37": 1363, "episode_38": 1179, "episode_39": 1465, "episode_40": 1442, "episode_41": 1443, "episode_42": 1313, "episode_43": 1277, "episode_44": 1314, "episode_45": 1380, "episode_46": 1279, "episode_47": 1282, "episode_48": 1434, "episode_49": 1536, "episode_50": 1336, "episode_51": 1308, "episode_52": 1350, "episode_53": 1348, "episode_54": 1279, "episode_55": 1303, "episode_56": 1318, "episode_57": 1301, "episode_58": 1393, "episode_59": 1454, "episode_60": 1341, "episode_61": 1295, "episode_62": 1380, "episode_63": 1436, "episode_64": 1157, "episode_65": 1370, "episode_66": 1356, "episode_67": 1510, "episode_68": 1293, "episode_69": 1289, "episode_70": 1273, "episode_71": 1259, "episode_72": 1307, "episode_73": 1369, "episode_74": 1287, "episode_75": 1383, "episode_76": 1223, "episode_77": 1316, "episode_78": 1393, "episode_79": 1329, "episode_80": 1279, "episode_81": 1422, "episode_82": 1330, "episode_83": 1237, "episode_84": 1622, "episode_85": 1360, "episode_86": 1468, "episode_87": 1215, "episode_88": 1410, "episode_89": 1255, "episode_90": 1248, "episode_91": 1311, "episode_92": 1253, "episode_93": 1250, "episode_94": 1301, "episode_95": 1397, "episode_96": 1308, "episode_97": 1393, "episode_98": 1443, "episode_99": 1250, "episode_100": 1269, "episode_101": 1356, "episode_102": 1349, "episode_103": 1272, "episode_104": 1294, "episode_105": 1253, "episode_106": 1526, "episode_107": 1567, "episode_108": 1281, "episode_109": 1432, "episode_110": 1405, "episode_111": 1465, "episode_112": 1373, "episode_113": 1301, "episode_114": 1349, "episode_115": 1408, "episode_116": 1341, "episode_117": 1282, "episode_118": 1294, "episode_119": 1454, "episode_120": 1229, "episode_121": 1242, "episode_122": 1308, "episode_123": 1218, "episode_124": 1466, "episode_125": 1266, "episode_126": 1365, "episode_127": 1270, "episode_128": 1393, "episode_129": 1247, "episode_130": 1387, "episode_131": 1372, "episode_132": 1358, "episode_133": 1323, "episode_134": 1349, "episode_135": 1262, "episode_136": 1388, "episode_137": 1450, "episode_138": 1230, "episode_139": 1525, "episode_140": 1366, "episode_141": 1359, "episode_142": 1352, "episode_143": 1337, "episode_144": 1271, "episode_145": 1526, "episode_146": 1201, "episode_147": 1419, "episode_148": 1457, "episode_149": 1259, "episode_150": 1395, "episode_151": 1357, "episode_152": 1265, "episode_153": 1375, "episode_154": 1397, "episode_155": 1378, "episode_156": 1441, "episode_157": 1349, "episode_158": 1374, "episode_159": 1233, "episode_160": 1278, "episode_161": 1458, "episode_162": 1239, "episode_163": 1273, "episode_164": 1249, "episode_165": 1198, "episode_166": 1270, "episode_167": 1306, "episode_168": 1389, "episode_169": 1223, "episode_170": 1506, "episode_171": 1449, "episode_172": 1282, "episode_173": 1400, "episode_174": 1368, "episode_175": 1271, "episode_176": 1304, "episode_177": 1260, "episode_178": 1258, "episode_179": 1304, "episode_180": 1393, "episode_181": 1181, "episode_182": 1288, "episode_183": 1339, "episode_184": 1366, "episode_185": 1302, "episode_186": 1396, "episode_187": 1423, "episode_188": 1226, "episode_189": 1291, "episode_190": 1367, "episode_191": 1420, "episode_192": 1363, "episode_193": 1273, "episode_194": 1275, "episode_195": 1306, "episode_196": 1331, "episode_197": 1290, "episode_198": 1297, "episode_199": 1369, "episode_200": 1364, "episode_201": 1444, "episode_202": 1274, "episode_203": 1316, "episode_204": 1221, "episode_205": 1316, "episode_206": 1194, "episode_207": 1269, "episode_208": 1314, "episode_209": 1365, "episode_210": 1328, "episode_211": 1472, "episode_212": 1430, "episode_213": 1326, "episode_214": 1261, "episode_215": 1259, "episode_216": 1402, "episode_217": 1412, "episode_218": 1425, "episode_219": 1209, "episode_220": 1277, "episode_221": 1345, "episode_222": 1237, "episode_223": 1212, "episode_224": 1337, "episode_225": 1402, "episode_226": 1345, "episode_227": 1327, "episode_228": 1167, "episode_229": 1260, "episode_230": 1299, "episode_231": 1448, "episode_232": 1354, "episode_233": 1293, "episode_234": 1383, "episode_235": 1469, "episode_236": 1440, "episode_237": 1250, "episode_238": 1451, "episode_239": 1437, "episode_240": 1510, "episode_241": 1305, "episode_242": 1300, "episode_243": 1366, "episode_244": 1307, "episode_245": 1300, "episode_246": 1543, "episode_247": 1438, "episode_248": 1304, "episode_249": 1263, "episode_250": 1269, "episode_251": 1232, "episode_252": 1474, "episode_253": 1389, "episode_254": 1237, "episode_255": 1467, "episode_256": 1363, "episode_257": 1303, "episode_258": 1264, "episode_259": 1402, "episode_260": 1276, "episode_261": 1258, "episode_262": 1432, "episode_263": 1336, "episode_264": 1265, "episode_265": 1267, "episode_266": 1462, "episode_267": 1266, "episode_268": 1341, "episode_269": 1373, "episode_270": 1380, "episode_271": 1326, "episode_272": 1390, "episode_273": 1360, "episode_274": 1295, "episode_275": 1292, "episode_276": 1336, "episode_277": 1271, "episode_278": 1359, "episode_279": 1313, "episode_280": 1364, "episode_281": 1283, "episode_282": 1302, "episode_283": 1389, "episode_284": 1333, "episode_285": 1315, "episode_286": 1315, "episode_287": 1351, "episode_288": 1463, "episode_289": 1339, "episode_290": 1238, "episode_291": 1341, "episode_292": 1400, "episode_293": 1290, "episode_294": 1331, "episode_295": 1307, "episode_296": 1342, "episode_297": 1295, "episode_298": 1313, "episode_299": 1308, "episode_300": 1524, "episode_301": 1325, "episode_302": 1267, "episode_303": 1350, "episode_304": 1403, "episode_305": 1256, "episode_306": 1346, "episode_307": 1443, "episode_308": 1331, "episode_309": 1346, "episode_310": 1573, "episode_311": 1339, "episode_312": 1265, "episode_313": 1381, "episode_314": 1377, "episode_315": 1494, "episode_316": 1331, "episode_317": 1278, "episode_318": 1315, "episode_319": 1389, "episode_320": 1518, "episode_321": 1328, "episode_322": 1473, "episode_323": 1388, "episode_324": 1192, "episode_325": 1231, "episode_326": 1320, "episode_327": 1340, "episode_328": 1402, "episode_329": 1404, "episode_330": 1301, "episode_331": 1229, "episode_332": 1378, "episode_333": 1347, "episode_334": 1361, "episode_335": 1314, "episode_336": 1341, "episode_337": 1435, "episode_338": 1329, "episode_339": 1313, "episode_340": 1283, "episode_341": 1370, "episode_342": 1252, "episode_343": 1338, "episode_344": 1232, "episode_345": 1263, "episode_346": 1462, "episode_347": 1256, "episode_348": 1413, "episode_349": 1328, "episode_350": 1508, "episode_351": 1315, "episode_352": 1289, "episode_353": 1276, "episode_354": 1451, "episode_355": 1259, "episode_356": 1309, "episode_357": 1314, "episode_358": 1315, "episode_359": 1315, "episode_360": 1360, "episode_361": 1335, "episode_362": 1455, "episode_363": 1386, "episode_364": 1346, "episode_365": 1381, "episode_366": 1306, "episode_367": 1522, "episode_368": 1419, "episode_369": 1407, "episode_370": 1223, "episode_371": 1187, "episode_372": 1330, "episode_373": 1359, "episode_374": 1269, "episode_375": 1305, "episode_376": 1492, "episode_377": 1255, "episode_378": 1202, "episode_379": 1457, "episode_380": 1329, "episode_381": 1296, "episode_382": 1345, "episode_383": 1457, "episode_384": 1344, "episode_385": 1346, "episode_386": 1353, "episode_387": 1294, "episode_388": 1238, "episode_389": 1333, "episode_390": 1469, "episode_391": 1222, "episode_392": 1258, "episode_393": 1394, "episode_394": 1386, "episode_395": 1317, "episode_396": 1327, "episode_397": 1313, "episode_398": 1455, "episode_399": 1385, "episode_400": 1243, "episode_401": 1285, "episode_402": 1341, "episode_403": 1355, "episode_404": 1374, "episode_405": 1405, "episode_406": 1352, "episode_407": 1187, "episode_408": 1346, "episode_409": 1329, "episode_410": 1309, "episode_411": 1340, "episode_412": 1214, "episode_413": 1316, "episode_414": 1325, "episode_415": 1335, "episode_416": 1279, "episode_417": 1309, "episode_418": 1268, "episode_419": 1524, "episode_420": 1408, "episode_421": 1325, "episode_422": 1420, "episode_423": 1352, "episode_424": 1284, "episode_425": 1298, "episode_426": 1438, "episode_427": 1334, "episode_428": 1228, "episode_429": 1446, "episode_430": 1277, "episode_431": 1290, "episode_432": 1235, "episode_433": 1350, "episode_434": 1327, "episode_435": 1363, "episode_436": 1306, "episode_437": 1344, "episode_438": 1261, "episode_439": 1341, "episode_440": 1243, "episode_441": 1271, "episode_442": 1447, "episode_443": 1292, "episode_444": 1287, "episode_445": 1241, "episode_446": 1323, "episode_447": 1398, "episode_448": 1568, "episode_449": 1279, "episode_450": 1326, "episode_451": 1395, "episode_452": 1265, "episode_453": 1227, "episode_454": 1267, "episode_455": 1207, "episode_456": 1451, "episode_457": 1473, "episode_458": 1262, "episode_459": 1452, "episode_460": 1495, "episode_461": 1418, "episode_462": 1412, "episode_463": 1398, "episode_464": 1230, "episode_465": 1352, "episode_466": 1241, "episode_467": 1244, "episode_468": 1266, "episode_469": 1230, "episode_470": 1402, "episode_471": 1378, "episode_472": 1445, "episode_473": 1360, "episode_474": 1313, "episode_475": 1333, "episode_476": 1336, "episode_477": 1333, "episode_478": 1457, "episode_479": 1327, "episode_480": 1314, "episode_481": 1219, "episode_482": 1398, "episode_483": 1428, "episode_484": 1254, "episode_485": 1513, "episode_486": 1386, "episode_487": 1368, "episode_488": 1279, "episode_489": 1206, "episode_490": 1496, "episode_491": 1442, "episode_492": 1375, "episode_493": 1357, "episode_494": 1410, "episode_495": 1266, "episode_496": 1303, "episode_497": 1294, "episode_498": 1352, "episode_499": 1314, "episode_500": 1292, "episode_501": 1347, "episode_502": 1398, "episode_503": 1264, "episode_504": 1522, "episode_505": 1332, "episode_506": 1203, "episode_507": 1256, "episode_508": 1373, "episode_509": 1305, "episode_510": 1225, "episode_511": 1222, "episode_512": 1416, "episode_513": 1286, "episode_514": 1269, "episode_515": 1307, "episode_516": 1513, "episode_517": 1474, "episode_518": 1336, "episode_519": 1417, "episode_520": 1574, "episode_521": 1245, "episode_522": 1320, "episode_523": 1253, "episode_524": 1232, "episode_525": 1295, "episode_526": 1323, "episode_527": 1258, "episode_528": 1406, "episode_529": 1227, "episode_530": 1270, "episode_531": 1256, "episode_532": 1289, "episode_533": 1246, "episode_534": 1402, "episode_535": 1335, "episode_536": 1272, "episode_537": 1218, "episode_538": 1246, "episode_539": 1308, "episode_540": 1311, "episode_541": 1328, "episode_542": 1399, "episode_543": 1291, "episode_544": 1313, "episode_545": 1372, "episode_546": 1440, "episode_547": 1220, "episode_548": 1392, "episode_549": 1246, "episode_550": 1276, "episode_551": 1318, "episode_552": 1200, "episode_553": 1334, "episode_554": 1323, "episode_555": 1347, "episode_556": 1262, "episode_557": 1368, "episode_558": 1311, "episode_559": 1314, "episode_560": 1349, "episode_561": 1263, "episode_562": 1284, "episode_563": 1480, "episode_564": 1298, "episode_565": 1548, "episode_566": 1243, "episode_567": 1563, "episode_568": 1214, "episode_569": 1217, "episode_570": 1380, "episode_571": 1292, "episode_572": 1282, "episode_573": 1379, "episode_574": 1265, "episode_575": 1702, "episode_576": 1249, "episode_577": 1408, "episode_578": 1491, "episode_579": 1228, "episode_580": 1386, "episode_581": 1250, "episode_582": 1219, "episode_583": 1373, "episode_584": 1448, "episode_585": 1284, "episode_586": 1297, "episode_587": 1290, "episode_588": 1260, "episode_589": 1317, "episode_590": 1365, "episode_591": 1313, "episode_592": 1443, "episode_593": 1306, "episode_594": 1426, "episode_595": 1370, "episode_596": 1306, "episode_597": 1436, "episode_598": 1239, "episode_599": 1296, "episode_600": 1326, "episode_601": 1395, "episode_602": 1461, "episode_603": 1253, "episode_604": 1455, "episode_605": 1578, "episode_606": 1368, "episode_607": 1301, "episode_608": 1395, "episode_609": 1585, "episode_610": 1250, "episode_611": 1290, "episode_612": 1156, "episode_613": 1261, "episode_614": 1328, "episode_615": 1212, "episode_616": 1368, "episode_617": 1384, "episode_618": 1381, "episode_619": 1298, "episode_620": 1301, "episode_621": 1252, "episode_622": 1282, "episode_623": 1251, "episode_624": 1272, "episode_625": 1470, "episode_626": 1277, "episode_627": 1288, "episode_628": 1380, "episode_629": 1363, "episode_630": 1265, "episode_631": 1270, "episode_632": 1283, "episode_633": 1324, "episode_634": 1600, "episode_635": 1405, "episode_636": 1305, "episode_637": 1291, "episode_638": 1336, "episode_639": 1206, "episode_640": 1258, "episode_641": 1339, "episode_642": 1413, "episode_643": 1351, "episode_644": 1347, "episode_645": 1361, "episode_646": 1264, "episode_647": 1406, "episode_648": 1232, "episode_649": 1380, "episode_650": 1282, "episode_651": 1593, "episode_652": 1347, "episode_653": 1343, "episode_654": 1484, "episode_655": 1324, "episode_656": 1462, "episode_657": 1260, "episode_658": 1299, "episode_659": 1362, "episode_660": 1184, "episode_661": 1453, "episode_662": 1472, "episode_663": 1467, "episode_664": 1334, "episode_665": 1387, "episode_666": 1216, "episode_667": 1320, "episode_668": 1367, "episode_669": 1241, "episode_670": 1394, "episode_671": 1273, "episode_672": 1276, "episode_673": 1272, "episode_674": 1315, "episode_675": 1314, "episode_676": 1316, "episode_677": 1520, "episode_678": 1423, "episode_679": 1349, "episode_680": 1293, "episode_681": 1419, "episode_682": 1261, "episode_683": 1427, "episode_684": 1321, "episode_685": 1448, "episode_686": 1231, "episode_687": 1292, "episode_688": 1233, "episode_689": 1390, "episode_690": 1362, "episode_691": 1347, "episode_692": 1265, "episode_693": 1484, "episode_694": 1257, "episode_695": 1278, "episode_696": 1252, "episode_697": 1497, "episode_698": 1263, "episode_699": 1334, "episode_700": 1381, "episode_701": 1319, "episode_702": 1377, "episode_703": 1270, "episode_704": 1286, "episode_705": 1337, "episode_706": 1298, "episode_707": 1376, "episode_708": 1307, "episode_709": 1255, "episode_710": 1287, "episode_711": 1247, "episode_712": 1352, "episode_713": 1262, "episode_714": 1358, "episode_715": 1292, "episode_716": 1431, "episode_717": 1266, "episode_718": 1456, "episode_719": 1294, "episode_720": 1322, "episode_721": 1284, "episode_722": 1423, "episode_723": 1249, "episode_724": 1375, "episode_725": 1365, "episode_726": 1467, "episode_727": 1214, "episode_728": 1242, "episode_729": 1398, "episode_730": 1289, "episode_731": 1425, "episode_732": 1304, "episode_733": 1138, "episode_734": 1253, "episode_735": 1316, "episode_736": 1244, "episode_737": 1429, "episode_738": 1375, "episode_739": 1302, "episode_740": 1398, "episode_741": 1288, "episode_742": 1311, "episode_743": 1252, "episode_744": 1480, "episode_745": 1271, "episode_746": 1288, "episode_747": 1254, "episode_748": 1349, "episode_749": 1268, "episode_750": 1371, "episode_751": 1431, "episode_752": 1289, "episode_753": 1206, "episode_754": 1404, "episode_755": 1431, "episode_756": 1539, "episode_757": 1436, "episode_758": 1396, "episode_759": 1267, "episode_760": 1412, "episode_761": 1313, "episode_762": 1327, "episode_763": 1246, "episode_764": 1205, "episode_765": 1364, "episode_766": 1400, "episode_767": 1590, "episode_768": 1233, "episode_769": 1309, "episode_770": 1321, "episode_771": 1371, "episode_772": 1466, "episode_773": 1352, "episode_774": 1300, "episode_775": 1274, "episode_776": 1317, "episode_777": 1446, "episode_778": 1272, "episode_779": 1438, "episode_780": 1313, "episode_781": 1515, "episode_782": 1369, "episode_783": 1348, "episode_784": 1330, "episode_785": 1301, "episode_786": 1384, "episode_787": 1385, "episode_788": 1267, "episode_789": 1333, "episode_790": 1294, "episode_791": 1403, "episode_792": 1440, "episode_793": 1382, "episode_794": 1356, "episode_795": 1411, "episode_796": 1263, "episode_797": 1366, "episode_798": 1379, "episode_799": 1242, "episode_800": 1304, "episode_801": 1326, "episode_802": 1299, "episode_803": 1338, "episode_804": 1310, "episode_805": 1236, "episode_806": 1433, "episode_807": 1431, "episode_808": 1280, "episode_809": 1234, "episode_810": 1303, "episode_811": 1252, "episode_812": 1305, "episode_813": 1391, "episode_814": 1379, "episode_815": 1459, "episode_816": 1468, "episode_817": 1302, "episode_818": 1243, "episode_819": 1400, "episode_820": 1335, "episode_821": 1384, "episode_822": 1304, "episode_823": 1214, "episode_824": 1253, "episode_825": 1424, "episode_826": 1355, "episode_827": 1450, "episode_828": 1260, "episode_829": 1393, "episode_830": 1314, "episode_831": 1288, "episode_832": 1371, "episode_833": 1334, "episode_834": 1320, "episode_835": 1357, "episode_836": 1353, "episode_837": 1415, "episode_838": 1286, "episode_839": 1240, "episode_840": 1430, "episode_841": 1395, "episode_842": 1317, "episode_843": 1343, "episode_844": 1304, "episode_845": 1363, "episode_846": 1398, "episode_847": 1325, "episode_848": 1240, "episode_849": 1345, "episode_850": 1371, "episode_851": 1176, "episode_852": 1411, "episode_853": 1302, "episode_854": 1297, "episode_855": 1318, "episode_856": 1227, "episode_857": 1324, "episode_858": 1274, "episode_859": 1378, "episode_860": 1409, "episode_861": 1254, "episode_862": 1358, "episode_863": 1270, "episode_864": 1208, "episode_865": 1225, "episode_866": 1269, "episode_867": 1311, "episode_868": 1372, "episode_869": 1225, "episode_870": 1326, "episode_871": 1279, "episode_872": 1355, "episode_873": 1260, "episode_874": 1324, "episode_875": 1263, "episode_876": 1326, "episode_877": 1284, "episode_878": 1351, "episode_879": 1413, "episode_880": 1221, "episode_881": 1337, "episode_882": 1313, "episode_883": 1445, "episode_884": 1539, "episode_885": 1266, "episode_886": 1198, "episode_887": 1495, "episode_888": 1358, "episode_889": 1249, "episode_890": 1499, "episode_891": 1490, "episode_892": 1334, "episode_893": 1395, "episode_894": 1164, "episode_895": 1456, "episode_896": 1360, "episode_897": 1341, "episode_898": 1531, "episode_899": 1315, "episode_900": 1460, "episode_901": 1405, "episode_902": 1244, "episode_903": 1374, "episode_904": 1330, "episode_905": 1370, "episode_906": 1554, "episode_907": 1617, "episode_908": 1336, "episode_909": 1367, "episode_910": 1371, "episode_911": 1464, "episode_912": 1431, "episode_913": 1379, "episode_914": 1421, "episode_915": 1289, "episode_916": 1237, "episode_917": 1263, "episode_918": 1306, "episode_919": 1336, "episode_920": 1298, "episode_921": 1389, "episode_922": 1339, "episode_923": 1375, "episode_924": 1354, "episode_925": 1321, "episode_926": 1237, "episode_927": 1448, "episode_928": 1243, "episode_929": 1377, "episode_930": 1557, "episode_931": 1342, "episode_932": 1222, "episode_933": 1415, "episode_934": 1382, "episode_935": 1307, "episode_936": 1209, "episode_937": 1490, "episode_938": 1365, "episode_939": 1395, "episode_940": 1285, "episode_941": 1296, "episode_942": 1269, "episode_943": 1581, "episode_944": 1255, "episode_945": 1327, "episode_946": 1486, "episode_947": 1434, "episode_948": 1308, "episode_949": 1338, "episode_950": 1355, "episode_951": 1350, "episode_952": 1181, "episode_953": 1269, "episode_954": 1410, "episode_955": 1331, "episode_956": 1418, "episode_957": 1384, "episode_958": 1291, "episode_959": 1291, "episode_960": 1230, "episode_961": 1263, "episode_962": 1322, "episode_963": 1309, "episode_964": 1332, "episode_965": 1182, "episode_966": 1240, "episode_967": 1260, "episode_968": 1469, "episode_969": 1386, "episode_970": 1390, "episode_971": 1181, "episode_972": 1337, "episode_973": 1443, "episode_974": 1259, "episode_975": 1409, "episode_976": 1240, "episode_977": 1309, "episode_978": 1426, "episode_979": 1393, "episode_980": 1371, "episode_981": 1363, "episode_982": 1272, "episode_983": 1209, "episode_984": 1242, "episode_985": 1282, "episode_986": 1373, "episode_987": 1385, "episode_988": 1366, "episode_989": 1506, "episode_990": 1206, "episode_991": 1245, "episode_992": 1217, "episode_993": 1316, "episode_994": 1203, "episode_995": 1264, "episode_996": 1360, "episode_997": 1249, "episode_998": 1321, "episode_999": 1313}}